image_classifier/ImageClassifier.py
image_classifier/__init__.py
image_feature_extractor-0.0.3.dist-info/LICENSE
image_feature_extractor-0.0.3.dist-info/METADATA
image_feature_extractor-0.0.3.dist-info/WHEEL
image_feature_extractor-0.0.3.dist-info/top_level.txt
image_feature_extractor-0.0.3.dist-info/RECORD
