Metadata-Version: 2.1
Name: image-feature-extractor
Version: 0.0.3
Summary: A feature extractor model that extracts features from input PIL image
Home-page: https://github.com/ayatarek1998/image_search
Author: Aya Tarek
Author-email: ayathehae@gmail.com
License: UNKNOWN
Platform: UNKNOWN
Classifier: Programming Language :: Python :: 3
Classifier: License :: OSI Approved :: MIT License
Classifier: Operating System :: OS Independent
Requires-Python: >=3.6
License-File: LICENSE
